moshimoshi/__init__.py
moshimoshi-0.2.1.dist-info/LICENSE.md
moshimoshi-0.2.1.dist-info/WHEEL
moshimoshi-0.2.1.dist-info/METADATA
moshimoshi-0.2.1.dist-info/RECORD
