Metadata-Version: 2.1
Name: moshimoshi
Version: 0.2.1
Summary: call a function in any python scripts using a formated string or json
Home-page: https://github.com/CircleOnCircles/moshimoshi
License: ISC
Author: Nutchanon Ninyawee
Author-email: me@nutchanon.org
Requires-Python: >=3.7,<4.0
Classifier: License :: OSI Approved
Classifier: Programming Language :: Python :: 3
Classifier: Programming Language :: Python :: 3.7
Classifier: Programming Language :: Python :: 3.8
Requires-Dist: loguru (>=0.5.3,<0.6.0)
Requires-Dist: parse_with_dot_access (>=1.17.1,<2.0.0)
Requires-Dist: pydantic (>=1.6.1,<2.0.0)
Project-URL: Repository, https://github.com/CircleOnCircles/moshimoshi
